[
  {"name": "Complete K_15, t=2", "graph": "complete", "t": 2, "seed": 1, "params": {"n": 15}},
  {"name": "Complete K_30, t=2", "graph": "complete", "t": 2, "seed": 2, "params": {"n": 30}},
  {"name": "Complete K_30, t=3", "graph": "complete", "t": 3, "seed": 3, "params": {"n": 30}},
  {"name": "Complete K_50, t=2", "graph": "complete", "t": 2, "seed": 10, "params": {"n": 50}},

  {"name": "Path P_30, t=2", "graph": "path", "t": 2, "seed": 11, "params": {"n": 30}},
  {"name": "Path P_50, t=2", "graph": "path", "t": 2, "seed": 12, "params": {"n": 50}},

  {"name": "8x8 grid, t=2", "graph": "grid", "t": 2, "seed": 4, "params": {"rows": 8, "cols": 8}},
  {"name": "8x8 grid, t=3", "graph": "grid", "t": 3, "seed": 5, "params": {"rows": 8, "cols": 8}},
  {"name": "10x10 grid, t=2", "graph": "grid", "t": 2, "seed": 6, "params": {"rows": 10, "cols": 10}},

  {"name": "Erdos-Renyi G(100, 500), t=2", "graph": "erdos_renyi", "t": 2, "seed": 7, "params": {"n": 100, "m": 500}},
  {"name": "Erdos-Renyi G(100, 500), t=3", "graph": "erdos_renyi", "t": 3, "seed": 8, "params": {"n": 100, "m": 500}},
  {"name": "Erdos-Renyi G(200, 1000), t=2", "graph": "erdos_renyi", "t": 2, "seed": 9, "params": {"n": 200, "m": 1000}}
]
